MANIFEST.in
README.rst
dev_requirements.txt
requirements.txt
setup.py
ella_attachments/__init__.py
ella_attachments/admin.py
ella_attachments/models.py
ella_attachments/newman_admin.py
ella_attachments/urls.py
ella_attachments/views.py
ella_attachments.egg-info/PKG-INFO
ella_attachments.egg-info/SOURCES.txt
ella_attachments.egg-info/dependency_links.txt
ella_attachments.egg-info/requires.txt
ella_attachments.egg-info/top_level.txt
ella_attachments/locale/cs/LC_MESSAGES/django.mo
ella_attachments/locale/cs/LC_MESSAGES/django.po
ella_attachments/locale/cs/LC_MESSAGES/static.mo
ella_attachments/locale/cs/LC_MESSAGES/static.po
ella_attachments/migrations/0001_initial.py
ella_attachments/migrations/0002_auto__chg_field_attachment_description__chg_field_attachment_type.py
ella_attachments/migrations/__init__.py
ella_attachments/templatetags/__init__.py
ella_attachments/templatetags/ella_attachments.py
test_ella_attachments/settings/__init__.py
test_ella_attachments/settings/base.py